tokenmonster.py
tokenmonster-1.1.6.dist-info/METADATA
tokenmonster-1.1.6.dist-info/WHEEL
tokenmonster-1.1.6.dist-info/top_level.txt
tokenmonster-1.1.6.dist-info/RECORD
