Metadata-Version: 2.1
Name: tokenmonster
Version: 1.1.6
Summary: Tokenize and decode text with TokenMonster vocabularies.
Home-page: https://github.com/alasdairforsythe/tokenmonster
Author: Alasdair Forsythe
Author-email: 77910352+alasdairforsythe@users.noreply.github.com
License: MIT
Platform: UNKNOWN
